{
  "meta": {
    "title": "2022年第2回 日本語 読解",
    "note": "由 PDF 扫描页导入。correct_choice 暂未录入；题型为初步标注。"
  },
  "questions": [
    {
      "id": "2022-2-Q01",
      "year": 2022,
      "era": "2022",
      "session": "第2回",
      "q_no": 1,
      "type_main": "focus",
      "type_sub": "原因理由",
      "center_word": "なぜ",
      "question_image": "assets/2022-2/pages/page_07.jpg",
      "page_images": ["assets/2022-2/pages/page_07.jpg"],
      "choice_count": 4,
      "correct_choice": null,
      "explanation": ""
    },
    {
      "id": "2022-2-Q02",
      "year": 2022,
      "era": "2022",
      "session": "第2回",
      "q_no": 2,
      "type_main": "consistency",
      "type_sub": "",
      "center_word": null,
      "question_image": "assets/2022-2/pages/page_08.jpg",
      "page_images": ["assets/2022-2/pages/page_08.jpg", "assets/2022-2/pages/page_09.jpg"],
      "choice_count": 4,
      "correct_choice": null,
      "explanation": "",
      "group_id": "2022-2-G02"
    },
    {
      "id": "2022-2-Q03",
      "year": 2022,
      "era": "2022",
      "session": "第2回",
      "q_no": 3,
      "type_main": "consistency",
      "type_sub": "",
      "center_word": null,
      "question_image": "assets/2022-2/pages/page_10.jpg",
      "page_images": ["assets/2022-2/pages/page_10.jpg"],
      "choice_count": 4,
      "correct_choice": null,
      "explanation": ""
    },
    {
      "id": "2022-2-Q04",
      "year": 2022,
      "era": "2022",
      "session": "第2回",
      "q_no": 4,
      "type_main": "focus",
      "type_sub": "中心词",
      "center_word": null,
      "question_image": "assets/2022-2/pages/page_11.jpg",
      "page_images": ["assets/2022-2/pages/page_11.jpg"],
      "choice_count": 4,
      "correct_choice": null,
      "explanation": ""
    },
    {
      "id": "2022-2-Q05",
      "year": 2022,
      "era": "2022",
      "session": "第2回",
      "q_no": 5,
      "type_main": "focus",
      "type_sub": "中心词",
      "center_word": null,
      "question_image": "assets/2022-2/pages/page_12.jpg",
      "page_images": ["assets/2022-2/pages/page_12.jpg"],
      "choice_count": 4,
      "correct_choice": null,
      "explanation": ""
    },
    {
      "id": "2022-2-Q06",
      "year": 2022,
      "era": "2022",
      "session": "第2回",
      "q_no": 6,
      "type_main": "consistency",
      "type_sub": "",
      "center_word": null,
      "question_image": "assets/2022-2/pages/page_13.jpg",
      "page_images": ["assets/2022-2/pages/page_13.jpg"],
      "choice_count": 4,
      "correct_choice": null,
      "explanation": ""
    },
    {
      "id": "2022-2-Q07",
      "year": 2022,
      "era": "2022",
      "session": "第2回",
      "q_no": 7,
      "type_main": "focus",
      "type_sub": "中心词",
      "center_word": null,
      "question_image": "assets/2022-2/pages/page_14.jpg",
      "page_images": ["assets/2022-2/pages/page_14.jpg"],
      "choice_count": 4,
      "correct_choice": null,
      "explanation": ""
    },
    {
      "id": "2022-2-Q08",
      "year": 2022,
      "era": "2022",
      "session": "第2回",
      "q_no": 8,
      "type_main": "focus",
      "type_sub": "中心词",
      "center_word": null,
      "question_image": "assets/2022-2/pages/page_15.jpg",
      "page_images": ["assets/2022-2/pages/page_15.jpg"],
      "choice_count": 4,
      "correct_choice": null,
      "explanation": ""
    },
    {
      "id": "2022-2-Q09",
      "year": 2022,
      "era": "2022",
      "session": "第2回",
      "q_no": 9,
      "type_main": "focus",
      "type_sub": "中心词",
      "center_word": null,
      "question_image": "assets/2022-2/pages/page_16.jpg",
      "page_images": ["assets/2022-2/pages/page_16.jpg"],
      "choice_count": 4,
      "correct_choice": null,
      "explanation": ""
    },
    {
      "id": "2022-2-Q10",
      "year": 2022,
      "era": "2022",
      "session": "第2回",
      "q_no": 10,
      "type_main": "consistency",
      "type_sub": "",
      "center_word": null,
      "question_image": "assets/2022-2/pages/page_17.jpg",
      "page_images": ["assets/2022-2/pages/page_17.jpg"],
      "choice_count": 4,
      "correct_choice": null,
      "explanation": ""
    },
    {
      "id": "2022-2-Q11",
      "year": 2022,
      "era": "2022",
      "session": "第2回",
      "q_no": 11,
      "type_main": "focus",
      "type_sub": "中心词",
      "center_word": null,
      "question_image": "assets/2022-2/pages/page_19.jpg",
      "page_images": ["assets/2022-2/pages/page_18.jpg", "assets/2022-2/pages/page_19.jpg"],
      "choice_count": 4,
      "correct_choice": null,
      "explanation": "",
      "group_id": "2022-2-G11-12"
    },
    {
      "id": "2022-2-Q12",
      "year": 2022,
      "era": "2022",
      "session": "第2回",
      "q_no": 12,
      "type_main": "consistency",
      "type_sub": "",
      "center_word": null,
      "question_image": "assets/2022-2/pages/page_19.jpg",
      "page_images": ["assets/2022-2/pages/page_18.jpg", "assets/2022-2/pages/page_19.jpg"],
      "choice_count": 4,
      "correct_choice": null,
      "explanation": "",
      "group_id": "2022-2-G11-12"
    },
    {
      "id": "2022-2-Q13",
      "year": 2022,
      "era": "2022",
      "session": "第2回",
      "q_no": 13,
      "type_main": "consistency",
      "type_sub": "",
      "center_word": null,
      "question_image": "assets/2022-2/pages/page_20.jpg",
      "page_images": ["assets/2022-2/pages/page_20.jpg"],
      "choice_count": 4,
      "correct_choice": null,
      "explanation": "",
      "group_id": "2022-2-G13-14"
    },
    {
      "id": "2022-2-Q14",
      "year": 2022,
      "era": "2022",
      "session": "第2回",
      "q_no": 14,
      "type_main": "consistency",
      "type_sub": "",
      "center_word": null,
      "question_image": "assets/2022-2/pages/page_20.jpg",
      "page_images": ["assets/2022-2/pages/page_20.jpg"],
      "choice_count": 4,
      "correct_choice": null,
      "explanation": "",
      "group_id": "2022-2-G13-14"
    },
    {
      "id": "2022-2-Q15",
      "year": 2022,
      "era": "2022",
      "session": "第2回",
      "q_no": 15,
      "type_main": "consistency",
      "type_sub": "",
      "center_word": null,
      "question_image": "assets/2022-2/pages/page_23.jpg",
      "page_images": ["assets/2022-2/pages/page_22.jpg", "assets/2022-2/pages/page_23.jpg"],
      "choice_count": 4,
      "correct_choice": null,
      "explanation": "",
      "group_id": "2022-2-G15-16"
    },
    {
      "id": "2022-2-Q16",
      "year": 2022,
      "era": "2022",
      "session": "第2回",
      "q_no": 16,
      "type_main": "focus",
      "type_sub": "中心词",
      "center_word": null,
      "question_image": "assets/2022-2/pages/page_23.jpg",
      "page_images": ["assets/2022-2/pages/page_22.jpg", "assets/2022-2/pages/page_23.jpg"],
      "choice_count": 4,
      "correct_choice": null,
      "explanation": "",
      "group_id": "2022-2-G15-16"
    },
    {
      "id": "2022-2-Q17",
      "year": 2022,
      "era": "2022",
      "session": "第2回",
      "q_no": 17,
      "type_main": "consistency",
      "type_sub": "",
      "center_word": null,
      "question_image": "assets/2022-2/pages/page_25.jpg",
      "page_images": ["assets/2022-2/pages/page_24.jpg", "assets/2022-2/pages/page_25.jpg"],
      "choice_count": 4,
      "correct_choice": null,
      "explanation": "",
      "group_id": "2022-2-G17-18"
    },
    {
      "id": "2022-2-Q18",
      "year": 2022,
      "era": "2022",
      "session": "第2回",
      "q_no": 18,
      "type_main": "consistency",
      "type_sub": "",
      "center_word": null,
      "question_image": "assets/2022-2/pages/page_25.jpg",
      "page_images": ["assets/2022-2/pages/page_24.jpg", "assets/2022-2/pages/page_25.jpg"],
      "choice_count": 4,
      "correct_choice": null,
      "explanation": "",
      "group_id": "2022-2-G17-18"
    },
    {
      "id": "2022-2-Q19",
      "year": 2022,
      "era": "2022",
      "session": "第2回",
      "q_no": 19,
      "type_main": "consistency",
      "type_sub": "",
      "center_word": null,
      "question_image": "assets/2022-2/pages/page_27.jpg",
      "page_images": ["assets/2022-2/pages/page_26.jpg", "assets/2022-2/pages/page_27.jpg"],
      "choice_count": 4,
      "correct_choice": null,
      "explanation": "",
      "group_id": "2022-2-G19-20"
    },
    {
      "id": "2022-2-Q20",
      "year": 2022,
      "era": "2022",
      "session": "第2回",
      "q_no": 20,
      "type_main": "consistency",
      "type_sub": "",
      "center_word": null,
      "question_image": "assets/2022-2/pages/page_27.jpg",
      "page_images": ["assets/2022-2/pages/page_26.jpg", "assets/2022-2/pages/page_27.jpg"],
      "choice_count": 4,
      "correct_choice": null,
      "explanation": "",
      "group_id": "2022-2-G19-20"
    },
    {
      "id": "2022-2-Q21",
      "year": 2022,
      "era": "2022",
      "session": "第2回",
      "q_no": 21,
      "type_main": "focus",
      "type_sub": "中心词",
      "center_word": null,
      "question_image": "assets/2022-2/pages/page_29.jpg",
      "page_images": ["assets/2022-2/pages/page_28.jpg", "assets/2022-2/pages/page_29.jpg"],
      "choice_count": 4,
      "correct_choice": null,
      "explanation": "",
      "group_id": "2022-2-G21-22"
    },
    {
      "id": "2022-2-Q22",
      "year": 2022,
      "era": "2022",
      "session": "第2回",
      "q_no": 22,
      "type_main": "consistency",
      "type_sub": "",
      "center_word": null,
      "question_image": "assets/2022-2/pages/page_29.jpg",
      "page_images": ["assets/2022-2/pages/page_28.jpg", "assets/2022-2/pages/page_29.jpg"],
      "choice_count": 4,
      "correct_choice": null,
      "explanation": "",
      "group_id": "2022-2-G21-22"
    },
    {
      "id": "2022-2-Q23",
      "year": 2022,
      "era": "2022",
      "session": "第2回",
      "q_no": 23,
      "type_main": "focus",
      "type_sub": "中心词",
      "center_word": null,
      "question_image": "assets/2022-2/pages/page_31.jpg",
      "page_images": ["assets/2022-2/pages/page_30.jpg", "assets/2022-2/pages/page_31.jpg"],
      "choice_count": 4,
      "correct_choice": null,
      "explanation": "",
      "group_id": "2022-2-G23-25"
    },
    {
      "id": "2022-2-Q24",
      "year": 2022,
      "era": "2022",
      "session": "第2回",
      "q_no": 24,
      "type_main": "focus",
      "type_sub": "中心词",
      "center_word": null,
      "question_image": "assets/2022-2/pages/page_31.jpg",
      "page_images": ["assets/2022-2/pages/page_30.jpg", "assets/2022-2/pages/page_31.jpg"],
      "choice_count": 4,
      "correct_choice": null,
      "explanation": "",
      "group_id": "2022-2-G23-25"
    },
    {
      "id": "2022-2-Q25",
      "year": 2022,
      "era": "2022",
      "session": "第2回",
      "q_no": 25,
      "type_main": "mainIdea",
      "type_sub": "",
      "center_word": null,
      "question_image": "assets/2022-2/pages/page_31.jpg",
      "page_images": ["assets/2022-2/pages/page_30.jpg", "assets/2022-2/pages/page_31.jpg"],
      "choice_count": 4,
      "correct_choice": null,
      "explanation": "",
      "group_id": "2022-2-G23-25"
    }
  ]
}
